typerhook/__init__.py
typerhook/hooks.py
typerhook/utils.py
typerhook-0.1.0.dist-info/METADATA
typerhook-0.1.0.dist-info/WHEEL
typerhook-0.1.0.dist-info/licenses/LICENSE
typerhook-0.1.0.dist-info/RECORD
