Metadata-Version: 2.4
Name: typerhook
Version: 0.1.0
Summary: Hooks for typer CLIs.
Project-URL: Homepage, https://github.com/muhamuhamuha/typerhook
Project-URL: Documentation, https://github.com/muhamuhamuha/typerhook#readme
Project-URL: Repository, https://github.com/muhamuhamuha/typerhook.git
Project-URL: Issues, https://github.com/muhamuhamuha/typerhook/issues
Author-email: muhamuhamuha <ahmedm357@hotmail.com>
License-Expression: MIT
License-File: LICENSE
Keywords: cli,command-line,decorator,parameters,typer
Classifier: Development Status :: 4 - Beta
Classifier: Intended Audience :: Developers
Classifier: License :: OSI Approved :: MIT License
Classifier: Operating System :: OS Independent
Classifier: Programming Language :: Python :: 3
Classifier: Programming Language :: Python :: 3.8
Classifier: Programming Language :: Python :: 3.9
Classifier: Programming Language :: Python :: 3.10
Classifier: Programming Language :: Python :: 3.11
Classifier: Programming Language :: Python :: 3.12
Classifier: Programming Language :: Python :: 3.13
Classifier: Topic :: Software Development :: Libraries :: Python Modules
Classifier: Topic :: Utilities
Requires-Python: >=3.8
Requires-Dist: typer>=0.16.0
Provides-Extra: dev
Requires-Dist: black; extra == 'dev'
Requires-Dist: isort; extra == 'dev'
Requires-Dist: mypy; extra == 'dev'
Requires-Dist: pytest-cov; extra == 'dev'
Requires-Dist: pytest>=8.4.1; extra == 'dev'
